layout_updater/LayoutUpdater.py
layout_updater/__init__.py
layout_updater/_imports_.py
layout_updater/layout_updater.min.js
layout_updater/layout_updater.min.js.map
layout_updater/metadata.json
layout_updater/package-info.json
layout_updater-0.0.14.dist-info/LICENSE
layout_updater-0.0.14.dist-info/METADATA
layout_updater-0.0.14.dist-info/WHEEL
layout_updater-0.0.14.dist-info/top_level.txt
layout_updater-0.0.14.dist-info/RECORD
