Metadata-Version: 2.1
Name: layout-updater
Version: 0.0.14
Summary: Project Description
Home-page: UNKNOWN
Author: Alex <jercan_alex27@yahoo.com>
License: MIT
Platform: UNKNOWN
Classifier: Framework :: Dash
License-File: LICENSE
